.travis.yml
CHANGES.txt
CONTRIBUTORS.txt
README.rst
bootstrap.py
buildout.cfg
setup.py
buildout-cache/downloads/.placeholder
buildout-cache/eggs/.placeholder
docs/LICENSE.GPL
docs/LICENSE.txt
src/collective/__init__.py
src/collective.diversion.egg-info/PKG-INFO
src/collective.diversion.egg-info/SOURCES.txt
src/collective.diversion.egg-info/dependency_links.txt
src/collective.diversion.egg-info/entry_points.txt
src/collective.diversion.egg-info/namespace_packages.txt
src/collective.diversion.egg-info/not-zip-safe
src/collective.diversion.egg-info/requires.txt
src/collective.diversion.egg-info/top_level.txt
src/collective/diversion/__init__.py
src/collective/diversion/configure.zcml
src/collective/diversion/diversion.py
src/collective/diversion/meta.zcml
src/collective/diversion/metadirectives.py
src/collective/diversion/tests/__init__.py
src/collective/diversion/tests/test_translation.py
src/collective/diversion/tests/test_zcml.py
src/collective/diversion/tests/test_zope_integration.py