Metadata-Version: 1.0
Name: collective.diversion
Version: 1.0
Summary: UNKNOWN
Home-page: https://github.com/collective/collective.diversion
Author: Matthew Wilkes
Author-email: matthew@matthewwilkes.co.uk
License: GPL
Keywords: Zope ZODB
Platform: UNKNOWN
Classifier: Framework :: Plone
Classifier: Topic :: Internet
Classifier: Topic :: Scientific/Engineering :: GIS
Classifier: Programming Language :: Python
